ecies/__init__.py
ecies/__main__.py
ecies/config.py
ecies/consts.py
ecies/keys/__init__.py
ecies/keys/helper.py
ecies/keys/private.py
ecies/keys/public.py
ecies/py.typed
ecies/utils/__init__.py
ecies/utils/elliptic.py
ecies/utils/eth.py
ecies/utils/hash.py
ecies/utils/hex.py
ecies/utils/symmetric.py
eciespy-0.4.5.dist-info/LICENSE
eciespy-0.4.5.dist-info/METADATA
eciespy-0.4.5.dist-info/WHEEL
eciespy-0.4.5.dist-info/entry_points.txt
eciespy-0.4.5.dist-info/RECORD
