Metadata-Version: 2.3
Name: eciespy
Version: 0.4.5
Summary: Elliptic Curve Integrated Encryption Scheme for secp256k1 in Python
License: MIT
Keywords: secp256k1,crypto,elliptic curves,ecies,bitcoin,ethereum,cryptocurrency
Author: Weiliang Li
Author-email: to.be.impressive@gmail.com
Maintainer: Weiliang Li
Maintainer-email: to.be.impressive@gmail.com
Requires-Python: >=3.9,<4.0
Classifier: Development Status :: 4 - Beta
Classifier: Intended Audience :: Developers
Classifier: License :: OSI Approved :: MIT License
Classifier: Natural Language :: English
Classifier: Operating System :: OS Independent
Classifier: Programming Language :: Python :: 3
Classifier: Programming Language :: Python :: 3.9
Classifier: Programming Language :: Python :: 3.10
Classifier: Programming Language :: Python :: 3.11
Classifier: Programming Language :: Python :: 3.12
Classifier: Programming Language :: Python :: 3.13
Classifier: Programming Language :: Python :: Implementation :: CPython
Classifier: Topic :: Security :: Cryptography
Provides-Extra: eth
Requires-Dist: coincurve (>=13,<22)
Requires-Dist: eth-keys (>=0.4,<0.8) ; extra == "eth"
Requires-Dist: pycryptodome (>=3.21.0)
Requires-Dist: typing-extensions (>=4.13.2,<5.0.0)
Project-URL: Repository, https://github.com/ecies/py
